[
  {
    "\ufeffvalue": "mark0",
    "_key": "!"
  },
  {
    "\ufeffvalue": "mark2",
    "_key": "#"
  },
  {
    "\ufeffvalue": "mark3",
    "_key": "$"
  },
  {
    "\ufeffvalue": "mark6",
    "_key": "&"
  },
  {
    "\ufeffvalue": "mark4",
    "_key": "."
  },
  {
    "\ufeffvalue": "0",
    "_key": "0"
  },
  {
    "\ufeffvalue": "1",
    "_key": "1"
  },
  {
    "\ufeffvalue": "2",
    "_key": "2"
  },
  {
    "\ufeffvalue": "3",
    "_key": "3"
  },
  {
    "\ufeffvalue": "4",
    "_key": "4"
  },
  {
    "\ufeffvalue": "5",
    "_key": "5"
  },
  {
    "\ufeffvalue": "6",
    "_key": "6"
  },
  {
    "\ufeffvalue": "7",
    "_key": "7"
  },
  {
    "\ufeffvalue": "8",
    "_key": "8"
  },
  {
    "\ufeffvalue": "9",
    "_key": "9"
  },
  {
    "\ufeffvalue": "mark1",
    "_key": "@"
  },
  {
    "\ufeffvalue": "mark5",
    "_key": "^"
  },
  {
    "\ufeffvalue": "a",
    "_key": "a"
  },
  {
    "\ufeffvalue": "b",
    "_key": "b"
  },
  {
    "\ufeffvalue": "c",
    "_key": "c"
  },
  {
    "\ufeffvalue": "d",
    "_key": "d"
  },
  {
    "\ufeffvalue": "e",
    "_key": "e"
  },
  {
    "\ufeffvalue": "f",
    "_key": "f"
  },
  {
    "\ufeffvalue": "g",
    "_key": "g"
  },
  {
    "\ufeffvalue": "h",
    "_key": "h"
  },
  {
    "\ufeffvalue": "i",
    "_key": "i"
  },
  {
    "\ufeffvalue": "j",
    "_key": "j"
  },
  {
    "\ufeffvalue": "k",
    "_key": "k"
  },
  {
    "\ufeffvalue": "l",
    "_key": "l"
  },
  {
    "\ufeffvalue": "m",
    "_key": "m"
  },
  {
    "\ufeffvalue": "n",
    "_key": "n"
  },
  {
    "\ufeffvalue": "o",
    "_key": "o"
  },
  {
    "\ufeffvalue": "p",
    "_key": "p"
  },
  {
    "\ufeffvalue": "q",
    "_key": "q"
  },
  {
    "\ufeffvalue": "r",
    "_key": "r"
  },
  {
    "\ufeffvalue": "s",
    "_key": "s"
  },
  {
    "\ufeffvalue": "t",
    "_key": "t"
  },
  {
    "\ufeffvalue": "u",
    "_key": "u"
  },
  {
    "\ufeffvalue": "v",
    "_key": "v"
  },
  {
    "\ufeffvalue": "w",
    "_key": "w"
  },
  {
    "\ufeffvalue": "x",
    "_key": "x"
  },
  {
    "\ufeffvalue": "y",
    "_key": "y"
  },
  {
    "\ufeffvalue": "z",
    "_key": "z"
  }
]