[
  {
    "\ufeffAllwaysLoaded": "0",
    "Bg1_Loop": "1",
    "Bg1_MoveRate": "0.1",
    "Bg2_Loop": "1",
    "Bg2_MoveRate": "0.3",
    "Bg3_Loop": "1",
    "Bg3_MoveRate": "0.6",
    "Bg4_Loop": "1",
    "Bg4_MoveRate": "1",
    "NextThemeId": "4",
    "ResourceKeyString": "tm01",
    "SnowEffectTexture": "",
    "SnowOffsetY": "",
    "SnowSize": "",
    "SnowSpeedY": "",
    "SnowTotalParticles": "",
    "SoundKeyString": "",
    "ThemeName": "1",
    "ThemeTime": "30",
    "ThemeType": "NormalStart",
    "_key": "1"
  },
  {
    "\ufeffAllwaysLoaded": "0",
    "Bg1_Loop": "1",
    "Bg1_MoveRate": "0.1",
    "Bg2_Loop": "1",
    "Bg2_MoveRate": "0.3",
    "Bg3_Loop": "1",
    "Bg3_MoveRate": "0.5",
    "Bg4_Loop": "1",
    "Bg4_MoveRate": "0.5",
    "NextThemeId": "6",
    "ResourceKeyString": "tm13",
    "SnowEffectTexture": "",
    "SnowOffsetY": "",
    "SnowSize": "",
    "SnowSpeedY": "",
    "SnowTotalParticles": "",
    "SoundKeyString": "",
    "ThemeName": "10",
    "ThemeTime": "50",
    "ThemeType": "Normal",
    "_key": "10"
  },
  {
    "\ufeffAllwaysLoaded": "0",
    "Bg1_Loop": "1",
    "Bg1_MoveRate": "0.03",
    "Bg2_Loop": "1",
    "Bg2_MoveRate": "0.06",
    "Bg3_Loop": "1",
    "Bg3_MoveRate": "0.1",
    "Bg4_Loop": "1",
    "Bg4_MoveRate": "1",
    "NextThemeId": "6",
    "ResourceKeyString": "tm09",
    "SnowEffectTexture": "",
    "SnowOffsetY": "",
    "SnowSize": "",
    "SnowSpeedY": "",
    "SnowTotalParticles": "",
    "SoundKeyString": "",
    "ThemeName": "11",
    "ThemeTime": "100",
    "ThemeType": "Normal",
    "_key": "11"
  },
  {
    "\ufeffAllwaysLoaded": "0",
    "Bg1_Loop": "1",
    "Bg1_MoveRate": "0.3",
    "Bg2_Loop": "1",
    "Bg2_MoveRate": "0.6",
    "Bg3_Loop": "1",
    "Bg3_MoveRate": "0.6",
    "Bg4_Loop": "1",
    "Bg4_MoveRate": "0",
    "NextThemeId": "4",
    "ResourceKeyString": "tm10",
    "SnowEffectTexture": "",
    "SnowOffsetY": "",
    "SnowSize": "",
    "SnowSpeedY": "",
    "SnowTotalParticles": "",
    "SoundKeyString": "",
    "ThemeName": "12",
    "ThemeTime": "30",
    "ThemeType": "Normal",
    "_key": "12"
  },
  {
    "\ufeffAllwaysLoaded": "0",
    "Bg1_Loop": "1",
    "Bg1_MoveRate": "0.1",
    "Bg2_Loop": "1",
    "Bg2_MoveRate": "0.3",
    "Bg3_Loop": "1",
    "Bg3_MoveRate": "0.6",
    "Bg4_Loop": "1",
    "Bg4_MoveRate": "1",
    "NextThemeId": "4",
    "ResourceKeyString": "tm11",
    "SnowEffectTexture": "xmas_particle2.png",
    "SnowOffsetY": "",
    "SnowSize": "",
    "SnowSpeedY": "",
    "SnowTotalParticles": "",
    "SoundKeyString": "",
    "ThemeName": "13",
    "ThemeTime": "30",
    "ThemeType": "Normal",
    "_key": "13"
  },
  {
    "\ufeffAllwaysLoaded": "0",
    "Bg1_Loop": "1",
    "Bg1_MoveRate": "0.1",
    "Bg2_Loop": "1",
    "Bg2_MoveRate": "0.3",
    "Bg3_Loop": "1",
    "Bg3_MoveRate": "0",
    "Bg4_Loop": "1",
    "Bg4_MoveRate": "0",
    "NextThemeId": "2",
    "ResourceKeyString": "tm02",
    "SnowEffectTexture": "",
    "SnowOffsetY": "",
    "SnowSize": "",
    "SnowSpeedY": "",
    "SnowTotalParticles": "",
    "SoundKeyString": "",
    "ThemeName": "2",
    "ThemeTime": "30",
    "ThemeType": "Normal",
    "_key": "2"
  },
  {
    "\ufeffAllwaysLoaded": "0",
    "Bg1_Loop": "1",
    "Bg1_MoveRate": "0.1",
    "Bg2_Loop": "1",
    "Bg2_MoveRate": "0.2",
    "Bg3_Loop": "1",
    "Bg3_MoveRate": "0.4",
    "Bg4_Loop": "1",
    "Bg4_MoveRate": "0.6",
    "NextThemeId": "2",
    "ResourceKeyString": "tm03",
    "SnowEffectTexture": "xmas_particle2.png",
    "SnowOffsetY": "",
    "SnowSize": "",
    "SnowSpeedY": "",
    "SnowTotalParticles": "",
    "SoundKeyString": "",
    "ThemeName": "3",
    "ThemeTime": "30",
    "ThemeType": "Normal",
    "_key": "3"
  },
  {
    "\ufeffAllwaysLoaded": "0",
    "Bg1_Loop": "1",
    "Bg1_MoveRate": "0.1",
    "Bg2_Loop": "1",
    "Bg2_MoveRate": "0.3",
    "Bg3_Loop": "1",
    "Bg3_MoveRate": "1",
    "Bg4_Loop": "1",
    "Bg4_MoveRate": "1",
    "NextThemeId": "3",
    "ResourceKeyString": "tm04",
    "SnowEffectTexture": "xmas_particle2.png",
    "SnowOffsetY": "",
    "SnowSize": "",
    "SnowSpeedY": "",
    "SnowTotalParticles": "",
    "SoundKeyString": "",
    "ThemeName": "4",
    "ThemeTime": "30",
    "ThemeType": "Normal",
    "_key": "4"
  },
  {
    "\ufeffAllwaysLoaded": "0",
    "Bg1_Loop": "1",
    "Bg1_MoveRate": "0.1",
    "Bg2_Loop": "1",
    "Bg2_MoveRate": "0.4",
    "Bg3_Loop": "1",
    "Bg3_MoveRate": "0.8",
    "Bg4_Loop": "1",
    "Bg4_MoveRate": "0.8",
    "NextThemeId": "4",
    "ResourceKeyString": "tm05",
    "SnowEffectTexture": "",
    "SnowOffsetY": "",
    "SnowSize": "",
    "SnowSpeedY": "",
    "SnowTotalParticles": "",
    "SoundKeyString": "",
    "ThemeName": "5",
    "ThemeTime": "30",
    "ThemeType": "Normal",
    "_key": "5"
  },
  {
    "\ufeffAllwaysLoaded": "0",
    "Bg1_Loop": "1",
    "Bg1_MoveRate": "0.1",
    "Bg2_Loop": "1",
    "Bg2_MoveRate": "0.3",
    "Bg3_Loop": "1",
    "Bg3_MoveRate": "0.6",
    "Bg4_Loop": "1",
    "Bg4_MoveRate": "1",
    "NextThemeId": "4",
    "ResourceKeyString": "tm12",
    "SnowEffectTexture": "xmas_particle2.png",
    "SnowOffsetY": "",
    "SnowSize": "",
    "SnowSpeedY": "",
    "SnowTotalParticles": "",
    "SoundKeyString": "",
    "ThemeName": "6",
    "ThemeTime": "30",
    "ThemeType": "Normal",
    "_key": "6"
  },
  {
    "\ufeffAllwaysLoaded": "0",
    "Bg1_Loop": "1",
    "Bg1_MoveRate": "0.1",
    "Bg2_Loop": "1",
    "Bg2_MoveRate": "0.2",
    "Bg3_Loop": "1",
    "Bg3_MoveRate": "0.5",
    "Bg4_Loop": "1",
    "Bg4_MoveRate": "0.8",
    "NextThemeId": "4",
    "ResourceKeyString": "tm06",
    "SnowEffectTexture": "",
    "SnowOffsetY": "",
    "SnowSize": "",
    "SnowSpeedY": "",
    "SnowTotalParticles": "",
    "SoundKeyString": "",
    "ThemeName": "7",
    "ThemeTime": "30",
    "ThemeType": "Normal",
    "_key": "7"
  },
  {
    "\ufeffAllwaysLoaded": "0",
    "Bg1_Loop": "0",
    "Bg1_MoveRate": "0.005",
    "Bg2_Loop": "1",
    "Bg2_MoveRate": "0.05",
    "Bg3_Loop": "1",
    "Bg3_MoveRate": "0.2",
    "Bg4_Loop": "1",
    "Bg4_MoveRate": "0.15",
    "NextThemeId": "5",
    "ResourceKeyString": "tm07",
    "SnowEffectTexture": "",
    "SnowOffsetY": "",
    "SnowSize": "",
    "SnowSpeedY": "",
    "SnowTotalParticles": "",
    "SoundKeyString": "",
    "ThemeName": "8",
    "ThemeTime": "30",
    "ThemeType": "Normal",
    "_key": "8"
  },
  {
    "\ufeffAllwaysLoaded": "1",
    "Bg1_Loop": "1",
    "Bg1_MoveRate": "0.1",
    "Bg2_Loop": "1",
    "Bg2_MoveRate": "0.6",
    "Bg3_Loop": "1",
    "Bg3_MoveRate": "0.5",
    "Bg4_Loop": "1",
    "Bg4_MoveRate": "0",
    "NextThemeId": "0",
    "ResourceKeyString": "tm81",
    "SnowEffectTexture": "",
    "SnowOffsetY": "",
    "SnowSize": "",
    "SnowSpeedY": "",
    "SnowTotalParticles": "",
    "SoundKeyString": "SoundBgm_FeverModeBgm",
    "ThemeName": "Bonus_Day",
    "ThemeTime": "9999",
    "ThemeType": "Bonus1",
    "_key": "81"
  },
  {
    "\ufeffAllwaysLoaded": "1",
    "Bg1_Loop": "1",
    "Bg1_MoveRate": "0.1",
    "Bg2_Loop": "1",
    "Bg2_MoveRate": "0.3",
    "Bg3_Loop": "1",
    "Bg3_MoveRate": "0.5",
    "Bg4_Loop": "1",
    "Bg4_MoveRate": "0",
    "NextThemeId": "0",
    "ResourceKeyString": "tm82",
    "SnowEffectTexture": "",
    "SnowOffsetY": "",
    "SnowSize": "",
    "SnowSpeedY": "",
    "SnowTotalParticles": "",
    "SoundKeyString": "SoundBgm_FeverModeBgm2",
    "ThemeName": "Bonus_Night",
    "ThemeTime": "9999",
    "ThemeType": "Bonus2",
    "_key": "82"
  },
  {
    "\ufeffAllwaysLoaded": "1",
    "Bg1_Loop": "1",
    "Bg1_MoveRate": "0.1",
    "Bg2_Loop": "1",
    "Bg2_MoveRate": "0.3",
    "Bg3_Loop": "1",
    "Bg3_MoveRate": "0.5",
    "Bg4_Loop": "1",
    "Bg4_MoveRate": "0",
    "NextThemeId": "0",
    "ResourceKeyString": "tm83",
    "SnowEffectTexture": "",
    "SnowOffsetY": "",
    "SnowSize": "",
    "SnowSpeedY": "",
    "SnowTotalParticles": "",
    "SoundKeyString": "SoundBgm_FeverModeBgm3",
    "ThemeName": "Bonus_Crazy",
    "ThemeTime": "9999",
    "ThemeType": "Bonus3",
    "_key": "83"
  },
  {
    "\ufeffAllwaysLoaded": "1",
    "Bg1_Loop": "1",
    "Bg1_MoveRate": "0.1",
    "Bg2_Loop": "1",
    "Bg2_MoveRate": "0.6",
    "Bg3_Loop": "1",
    "Bg3_MoveRate": "0.5",
    "Bg4_Loop": "1",
    "Bg4_MoveRate": "0",
    "NextThemeId": "0",
    "ResourceKeyString": "tm81_ch36",
    "SnowEffectTexture": "",
    "SnowOffsetY": "",
    "SnowSize": "",
    "SnowSpeedY": "",
    "SnowTotalParticles": "",
    "SoundKeyString": "SoundBgm_FeverModeBgm",
    "ThemeName": "Bonus_Day",
    "ThemeTime": "9999",
    "ThemeType": "Bonus1",
    "_key": "84"
  },
  {
    "\ufeffAllwaysLoaded": "1",
    "Bg1_Loop": "1",
    "Bg1_MoveRate": "0.1",
    "Bg2_Loop": "1",
    "Bg2_MoveRate": "0.3",
    "Bg3_Loop": "1",
    "Bg3_MoveRate": "0.5",
    "Bg4_Loop": "1",
    "Bg4_MoveRate": "0",
    "NextThemeId": "0",
    "ResourceKeyString": "tm82_ch36",
    "SnowEffectTexture": "",
    "SnowOffsetY": "",
    "SnowSize": "",
    "SnowSpeedY": "",
    "SnowTotalParticles": "",
    "SoundKeyString": "SoundBgm_FeverModeBgm2",
    "ThemeName": "Bonus_Night",
    "ThemeTime": "9999",
    "ThemeType": "Bonus2",
    "_key": "85"
  },
  {
    "\ufeffAllwaysLoaded": "1",
    "Bg1_Loop": "1",
    "Bg1_MoveRate": "0.1",
    "Bg2_Loop": "1",
    "Bg2_MoveRate": "0.3",
    "Bg3_Loop": "1",
    "Bg3_MoveRate": "0.5",
    "Bg4_Loop": "1",
    "Bg4_MoveRate": "0",
    "NextThemeId": "0",
    "ResourceKeyString": "tm83_ch36",
    "SnowEffectTexture": "",
    "SnowOffsetY": "",
    "SnowSize": "",
    "SnowSpeedY": "",
    "SnowTotalParticles": "",
    "SoundKeyString": "SoundBgm_FeverModeBgm3",
    "ThemeName": "Bonus_Crazy",
    "ThemeTime": "9999",
    "ThemeType": "Bonus3",
    "_key": "86"
  },
  {
    "\ufeffAllwaysLoaded": "0",
    "Bg1_Loop": "1",
    "Bg1_MoveRate": "0.1",
    "Bg2_Loop": "1",
    "Bg2_MoveRate": "0.3",
    "Bg3_Loop": "1",
    "Bg3_MoveRate": "0.6",
    "Bg4_Loop": "1",
    "Bg4_MoveRate": "1",
    "NextThemeId": "4",
    "ResourceKeyString": "tm08",
    "SnowEffectTexture": "xmas_particle2.png",
    "SnowOffsetY": "",
    "SnowSize": "",
    "SnowSpeedY": "",
    "SnowTotalParticles": "",
    "SoundKeyString": "",
    "ThemeName": "9",
    "ThemeTime": "30",
    "ThemeType": "Normal",
    "_key": "9"
  }
]